pyplot_themes/__init__.py
pyplot_themes/__version__.py
pyplot_themes/palettes.py
pyplot_themes/rcmod.py
pyplot_themes/themes.py
pyplot_themes-0.2.2.dist-info/LICENSE
pyplot_themes-0.2.2.dist-info/METADATA
pyplot_themes-0.2.2.dist-info/WHEEL
pyplot_themes-0.2.2.dist-info/top_level.txt
pyplot_themes-0.2.2.dist-info/RECORD
