Metadata-Version: 2.1
Name: pyplot-themes
Version: 0.2.2
Summary: Easily set themes that automatically apply to matplotlib, seaborn, and pandas plots
Home-page: https://github.com/raybuhr/pyplot-themes
Author: Ray Buhr
Author-email: raymond.buhr@gmail.com
License: MIT
Platform: UNKNOWN
Classifier: License :: OSI Approved :: MIT License
Classifier: Programming Language :: Python
Classifier: Programming Language :: Python :: 3
Classifier: Programming Language :: Python :: 3.6
Classifier: Programming Language :: Python :: Implementation :: CPython
Classifier: Programming Language :: Python :: Implementation :: PyPy
Requires-Python: >=3.6.0
Requires-Dist: matplotlib
